splendor/__init__.py
splendor/assets.py
splendor/blurry_mipmaps.py
splendor/camera.py
splendor/core.py
splendor/download.py
splendor/exceptions.py
splendor/frame_buffer.py
splendor/home.py
splendor/image.py
splendor/interactive_camera.py
splendor/json_numpy.py
splendor/mask_viewer.py
splendor/masks.py
splendor/obj_mesh.py
splendor/pose.py
splendor/primitives.py
splendor/render.py
splendor/shader_library.py
splendor/viewer.py
splendor/contexts/__init__.py
splendor/contexts/egl.py
splendor/contexts/glut.py
splendor/contexts/initialization.py
splendor/image_light/__init__.py
splendor/image_light/diffuse.py
splendor/image_light/panorama.py
splendor/scripts/__init__.py
splendor/scripts/panorama_to_image_light.py
splendor/scripts/panorama_to_strip.py
splendor/scripts/reflect_to_diffuse.py
splendor/scripts/splendor_asset_installer.py
splendor/scripts/splendor_mask_inspector.py
splendor/scripts/splendor_render.py
splendor/scripts/splendor_viewer.py
splendor/scripts/triangulate_obj.py
splendor/shaders/__init__.py
splendor/shaders/background.py
splendor/shaders/color_render.py
splendor/shaders/coord_render.py
splendor/shaders/depthmap.py
splendor/shaders/image_light.py
splendor/shaders/lighting_model.py
splendor/shaders/mask_render.py
splendor/shaders/mesh.py
splendor/shaders/pbr.py
splendor/shaders/skybox.py
splendor/shaders/utils.py
splendor_render-0.3.3.dist-info/LICENSE
splendor_render-0.3.3.dist-info/METADATA
splendor_render-0.3.3.dist-info/WHEEL
splendor_render-0.3.3.dist-info/entry_points.txt
splendor_render-0.3.3.dist-info/top_level.txt
splendor_render-0.3.3.dist-info/zip-safe
splendor_render-0.3.3.dist-info/RECORD
