Metadata-Version: 2.1
Name: splendor-render
Version: 0.3.3
Summary: A fancy shiny python renderer
Home-page: https://github.com/aaronwalsman/splendor-render
Author: Aaron Walsman
Author-email: aaronwalsman@gmail.com
Classifier: Programming Language :: Python :: 3
Classifier: License :: OSI Approved :: MIT License
Classifier: Operating System :: OS Independent
Requires-Python: >=3.6
License-File: LICENSE
Requires-Dist: Pillow
Requires-Dist: numpy
Requires-Dist: gdown
Requires-Dist: PyOpenGL (>=3.1.5)
Requires-Dist: tqdm
